setup.py
music/__init__.py
music/admin.py
music/apps.py
music/models.py
music/tests.py
music/urls.py
music/views.py
nrx_website.egg-info/PKG-INFO
nrx_website.egg-info/SOURCES.txt
nrx_website.egg-info/dependency_links.txt
nrx_website.egg-info/requires.txt
nrx_website.egg-info/top_level.txt