Metadata-Version: 1.1
Name: nrx-website
Version: 1.0.3
Summary: A dummy music album details
Home-page: UNKNOWN
Author: Neeraj Prasad
Author-email: neerajnitk.it@gmail.com
License: MIT
Keywords: music detail
Platform: UNKNOWN
Classifier: Development Status :: 4 - Beta
Classifier: Intended Audience :: Developers
Classifier: Topic :: Internet
Classifier: License :: OSI Approved :: MIT License
Classifier: Programming Language :: Python
Classifier: Programming Language :: Python :: 2
Classifier: Programming Language :: Python :: 2.6
Classifier: Programming Language :: Python :: 2.7
Classifier: Programming Language :: Python :: 3
Classifier: Programming Language :: Python :: 3.3
Classifier: Programming Language :: Python :: 3.4
Classifier: Programming Language :: Python :: 3.5
